{"slug": "dissociation-and-trauma-what-it-feels-like-and-how-to-come-back", "title": "Dissociation and Trauma: What It Feels Like and How to Come Back", "category": "Trauma Therapy", "excerpt": "Explore the experience of dissociation in trauma and learn practical, somatic-based ways to regain connection with your body and mind.", "readTime": "8 min read", "body": "<h2>Understanding Dissociation: The Body's Way of Coping</h2>\n<p>Dissociation is a complex, often misunderstood response to trauma. It acts as a psychological and physiological defense mechanism, allowing a person to detach from the overwhelming reality of their experience. As Bessel van der Kolk, author of <em>The Body Keeps the Score</em>, explains, dissociation is the mind’s way of protecting itself when the body and brain are flooded with unbearable stress.</p>\n<p>When trauma overwhelms the nervous system, dissociation can feel like a fog, a numbness, or a sense of being disconnected from your own body or reality. For some, it shows up as memory gaps; for others, it’s a feeling of watching your life from the outside, as if you’re not really “there.”</p>\n\n<h2>What Dissociation Feels Like: Voices from the Body</h2>\n<p>People who experience dissociation often describe it in terms like:</p>\n<ul>\n  <li>Feeling like a ghost inside your own body</li>\n  <li>Time slipping away or moments feeling unreal</li>\n  <li>Emotional numbness or a sense of being ‘shut down’</li>\n  <li>Out-of-body experiences or looking at yourself from a distance</li>\n  <li>Difficulty recalling what happened during traumatic events</li>\n</ul>\n<p>Peter Levine, founder of Somatic Experiencing, points out that dissociation is not a sign of mental illness but an adaptive survival strategy. It’s the nervous system’s way of freezing or escaping when fight or flight isn’t possible.</p>\n\n<h2>The Neuroscience Behind Dissociation</h2>\n<p>Stephen Porges’ Polyvagal Theory offers crucial insight into how dissociation arises from the nervous system’s hierarchical response to threat. When both fight and flight responses are unavailable or ineffective, the dorsal vagal complex—part of the parasympathetic nervous system—engages, leading to shutdown and dissociation.</p>\n<p>Dan Siegel, a leader in interpersonal neurobiology, highlights how dissociation disrupts integration across brain regions, fragmenting experience and sense of self. This fragmentation can make it challenging to stay grounded in the present or to access emotions safely.</p>\n\n<h2>Dissociation as a Barrier in Trauma Recovery</h2>\n<p>While dissociation protects in the moment, it can become a barrier when healing trauma. It prevents full processing of traumatic memories because those experiences remain split off from conscious awareness.</p>\n<p>Pat Ogden, a pioneer in somatic psychology, emphasizes the importance of reconnecting with the body to heal dissociation. Trauma is stored in the body, and only through somatic awareness can these dissociated parts be integrated.</p>\n\n<h2>How to Come Back: Somatic Tools for Grounding and Integration</h2>\n<p>Coming back from dissociation means re-establishing safety in your body and nervous system. Here are practical, research-backed methods to start that process:</p>\n<ul>\n  <li><strong>Tracking Sensations:</strong> Notice subtle physical sensations without judgment. This builds interoception, the sense of the body’s internal state, which Dan Siegel calls essential for integration.</li>\n  <li><strong>Grounding Exercises:</strong> Techniques like feeling your feet on the floor, noticing textures, or controlled breathing help engage the ventral vagal state—a calm, connected nervous system state described by Stephen Porges.</li>\n  <li><strong>Movement and Expression:</strong> Gentle movement, stretching, or shaking can discharge trauma energy held in the body, a core principle in Peter Levine’s Somatic Experiencing.</li>\n  <li><strong>Safe Relational Connection:</strong> Healing is often relational. Deb Dana’s work shows how attuned relationships regulate the nervous system, making it easier to stay present.</li>\n</ul>\n\n<h2>Using Internal Family Systems (IFS) to Understand Dissociated Parts</h2>\n<p>Richard Schwartz’s Internal Family Systems model offers a compassionate framework for working with dissociation. Instead of trying to eliminate dissociated parts, IFS invites you to acknowledge and dialogue with them. This acceptance reduces internal conflict and fosters integration.</p>\n<p>In trauma, some parts may carry pain, fear, or protective roles. Recognizing these roles helps you meet these parts with curiosity rather than fear.</p>\n\n<h2>Avoiding Common Pitfalls: Why Traditional Talk Therapy May Not Be Enough</h2>\n<p>Many who have tried traditional therapy find themselves stuck because talk therapy alone often can’t reach dissociated or somatically stored trauma. Francine Shapiro’s EMDR therapy is one exception that uses bilateral stimulation to access and process trauma safely.</p>\n<p>However, without somatic regulation and nervous system work, trauma can remain lodged in the body, causing symptoms like anxiety, numbness, or flashbacks.</p>\n\n<h2>Final Thoughts: Reclaiming Presence and Wholeness</h2>\n<blockquote>\"Dissociation isn’t a failure—it’s a survival strategy. Healing demands we gently return to our bodies, learning to feel safe again, step by step.\" – The Oracle Lover</blockquote>\n<p>Recovering from dissociation takes patience and a willingness to meet your body where it is. Grounding in the present, building nervous system resilience, and integrating dissociated parts can restore a coherent sense of self.</p>\n<p>As Gabor Maté reminds us, trauma recovery isn’t about erasing pain but about deeply understanding and compassionately working with the body’s wisdom. Somatic healing offers a path back to your life, your presence, and your aliveness.</p>\n<p>For those feeling stuck after therapy, incorporating somatic approaches alongside psychological insight can unlock new doors to healing.</p>", "faqs": [{"q": "What is dissociation in trauma?", "a": "Dissociation is a protective response to overwhelming trauma where the mind disconnects from the body or reality to shield itself from distressing experiences."}, {"q": "How does dissociation affect the body?", "a": "Dissociation can cause numbness, out-of-body sensations, or memory gaps, reflecting the nervous system's shutdown or freeze response to threat."}, {"q": "Can somatic healing help with dissociation?", "a": "Yes, somatic healing focuses on reconnecting with bodily sensations and regulating the nervous system, which are essential for integrating dissociated trauma parts."}, {"q": "Why might talk therapy alone not resolve dissociation?", "a": "Because dissociation involves bodily and neurological disconnection, talk therapy without somatic or nervous system regulation often can’t access or integrate these split-off parts."}], "affiliateProducts": [{"title": "The Body Keeps the Score by Bessel van der Kolk", "asin": "0143127748", "description": "A foundational book explaining how trauma affects the body and mind, offering insights crucial for somatic healing."}], "metaTitle": "Dissociation and Trauma: How to Heal and Ground Yourself", "metaDescription": "Learn what dissociation feels like in trauma and discover somatic tools to come back to your body and heal effectively.", "hero_url": "https://somatic-forlife.b-cdn.net/images/hero-trauma-therapy.webp", "author": "The Oracle Lover"}