{"slug": "somatic-therapy-for-survivors-of-childhood-emotional-neglect-by-peer-culture", "title": "Somatic Therapy for Survivors of Childhood Emotional Neglect by Peer Culture", "category": "Trauma Therapy", "excerpt": "Discover how somatic therapy helps survivors of childhood emotional neglect caused by peer culture heal body and mind.", "readTime": "9 min read", "body": "<h2>Understanding Childhood Emotional Neglect by Peer Culture</h2><p>Childhood emotional neglect (CEN) is often thought of as a failure of parents or primary caregivers to provide emotional support. However, peer culture during childhood and adolescence can also play a significant role in emotional neglect. When a child is excluded, bullied, or ignored by peers, their emotional needs for connection, validation, and safety go unmet. This form of neglect is less visible than overt abuse but has profound effects on the nervous system and emotional development.</p><p>Unlike physical abuse, emotional neglect by peers doesn’t leave bruises or scars but imprints on the body and brain. Bessel van der Kolk, a leading trauma researcher, reminds us that trauma is stored in the body, not just the mind. When children repeatedly experience emotional rejection or invisibility, their nervous system adapts by shutting down or becoming hypervigilant, leading to long-term dysregulation.</p><h2>How Peer Emotional Neglect Impacts the Nervous System</h2><p>Stephen Porges’ Polyvagal Theory provides a useful framework to understand this impact. The autonomic nervous system has three states: safe/social engagement, fight/flight mobilization, and shutdown/freezing. Chronic emotional neglect by peers can push a child’s nervous system into a persistent state of shutdown (dorsal vagal) or hyperarousal (sympathetic activation).</p><p>Children who are left out or bullied may learn to suppress their emotional expression to avoid further rejection, leading to internalized shame and disconnection from bodily sensations. This disconnection interferes with natural nervous system regulation and emotional processing, which Deb Dana, a clinical social worker and Polyvagal expert, emphasizes is critical for healing trauma.</p><h2>Why Traditional Talk Therapy Often Falls Short</h2><p>Many survivors of peer-related CEN have tried talk therapy but still feel stuck. This is often because their trauma is held in the body and nervous system rather than in conscious thought alone. Francine Shapiro’s work with EMDR shows how accessing sensory and somatic memories can unlock stuck trauma, but not all talk therapies integrate body-based approaches.</p><p>Pat Ogden’s sensorimotor psychotherapy and Peter Levine’s Somatic Experiencing are two modalities that directly address the body's role in trauma. These therapies help clients develop awareness of bodily sensations and learn to regulate their nervous system responses, which is essential for survivors of emotional neglect where the body learned to shut down or hyperactivate in response to peer rejection.</p><h2>The Role of Somatic Therapy in Healing Emotional Neglect from Peer Culture</h2><p>Somatic therapy focuses on the mind-body connection, helping survivors reconnect with their bodies and process trauma stored in physical form. It offers tools to notice subtle bodily cues that indicate nervous system states, and through guided exercises, clients learn to shift from states of shutdown or hyperarousal toward safety and regulation.</p><p>Somatic approaches intentionally cultivate present-moment awareness and nervous system regulation, empowering survivors to reclaim their capacity for connection and emotional expression. This process aligns with Dan Siegel’s concept of \"mindsight,\" the ability to perceive one’s own internal experience, which is often dulled in those with early emotional neglect.</p><h3>Key Somatic Techniques for Survivors of Peer Emotional Neglect</h3><ul><li><strong>Body Awareness and Tracking:</strong> Learning to identify sensations like tightness, numbness, or tingling that signal nervous system responses.</li><li><strong>Breath Regulation:</strong> Using breath to engage the parasympathetic nervous system and promote calm.</li><li><strong>Grounding and Centering:</strong> Techniques that reorient attention to the present and physical safety.</li><li><strong>Movement and Expression:</strong> Gentle movements or vocalizations to release stored tension and reestablish agency.</li><li><strong>Resourcing:</strong> Building internal and external supports that evoke safety, such as imagining a safe place or recalling supportive relationships.</li></ul><h2>Integrating Internal Family Systems to Address Internalized Neglect</h2><p>Survivors of peer emotional neglect often develop harsh inner critics or parts that dismiss their worth and needs. Richard Schwartz’s Internal Family Systems (IFS) model helps identify these internalized voices and foster compassionate self-leadership.</p><p>By combining somatic awareness with IFS, clients can feel the bodily sensations linked to these internalized parts, learn to witness them without judgment, and gradually transform self-neglect into self-care. This integration is vital because neglect by peers often creates fragmented self-experiences that purely cognitive approaches struggle to resolve.</p><h2>The Importance of Safety and Trust in Somatic Healing</h2><p>Gabor Maté highlights that trauma recovery depends on establishing a sense of safety in the therapeutic relationship and within the body. For survivors of peer emotional neglect, trust can be fragile due to early social rejection.</p><p>Somatic therapy sessions emphasize creating an environment where clients feel seen, heard, and safe to explore bodily sensations without overwhelm. This safety supports nervous system regulation and allows the trauma held in the body to be released or integrated.</p><blockquote>“Healing trauma requires reestablishing safety at the level of the body, not just the mind.” — Bessel van der Kolk</blockquote><h2>Practical Steps for Self-Directed Somatic Healing</h2><p>For survivors who want to begin healing on their own, here are evidence-based somatic practices informed by trauma experts:</p><ul><li><strong>Daily Body Check-Ins:</strong> Spend 5 minutes noticing what sensations are present in your body without trying to change them.</li><li><strong>Breath Exercises:</strong> Practice slow, deep diaphragmatic breathing to engage the vagus nerve and calm the nervous system.</li><li><strong>Grounding Techniques:</strong> Use the 5-4-3-2-1 sensory method to anchor yourself in the present during moments of distress.</li><li><strong>Movement:</strong> Gentle yoga, walking, or shaking out tension can help discharge stuck energy.</li><li><strong>Journaling with Body Awareness:</strong> Reflect on emotional experiences alongside bodily sensations to build mind-body integration.</li></ul><p>These practices create a foundation for nervous system regulation and increased emotional resilience. For deeper work, pairing self-directed practices with a trained somatic therapist who understands trauma is highly recommended.</p><h2>Conclusion: Reclaiming Connection Beyond Peer Neglect</h2><p>Childhood emotional neglect by peer culture leaves invisible wounds that traditional talk therapy often misses. Somatic therapy provides a powerful, body-based path to healing these wounds by addressing the nervous system dysregulation and internalized self-criticism that result from emotional invisibility and rejection.</p><p>By learning to listen to the body, regulate nervous system states, and compassionately engage internal parts, survivors of peer emotional neglect can reclaim their sense of safety, worth, and connection. This process takes time and patience but offers lasting transformation beyond the limits of words alone.</p><p>As trauma researchers and clinicians like Peter Levine, Pat Ogden, and Deb Dana illustrate, true healing requires engaging the whole person—mind, body, and relational context. For those ready to do this deep, somatic work, recovery is possible.</p>", "faqs": [{"q": "What is childhood emotional neglect by peer culture?", "a": "It refers to the emotional neglect a child experiences when peers exclude, ignore, or reject them, leaving emotional needs unmet despite no overt abuse."}, {"q": "How does somatic therapy help with emotional neglect?", "a": "Somatic therapy helps survivors reconnect with bodily sensations, regulate their nervous system, and process trauma stored in the body rather than just the mind."}, {"q": "Why might traditional talk therapy not be enough for CEN survivors?", "a": "Because trauma from emotional neglect is often held in the body and nervous system, talk therapy alone may not access or resolve these nonverbal, somatic memories."}, {"q": "Can I practice somatic healing on my own?", "a": "Yes, beginning with breathwork, body awareness, grounding, and gentle movement can support nervous system regulation, though working with a somatic therapist is ideal for deeper healing."}], "affiliateProducts": [{"title": "The Body Keeps the Score by Bessel van der Kolk", "asin": "B007Z6H3P8", "description": "A foundational book explaining how trauma is stored in the body and how somatic approaches can aid healing."}, {"title": "Waking the Tiger: Healing Trauma by Peter Levine", "asin": "B000OZMSYC", "description": "Introduces Somatic Experiencing techniques to release trauma held in the body."}], "metaTitle": "Somatic Therapy for Childhood Emotional Neglect", "metaDescription": "Learn how somatic therapy heals survivors of childhood emotional neglect caused by peer culture through body-based trauma recovery.", "hero_url": "https://somatic-forlife.b-cdn.net/images/hero-trauma-therapy.webp", "author": "The Oracle Lover"}