{"slug": "somatic-therapy-for-survivors-of-immigration-trauma", "title": "Somatic Therapy for Survivors of Immigration Trauma", "category": "Trauma Therapy", "excerpt": "Explore how somatic therapy aids survivors of immigration trauma by regulating the nervous system and healing the body’s trauma imprint.", "readTime": "9 min read", "body": "<h2>Understanding Immigration Trauma and Its Impact</h2><p>Immigration trauma is a complex, multifaceted experience that affects millions worldwide. It encompasses the distress caused by forced displacement, dangerous journeys, separation from loved ones, detention, and the ongoing stressors of acculturation and uncertainty. Survivors often carry not only psychological wounds but also deep somatic imprints—physical sensations, dysregulated nervous systems, and chronic stress responses that traditional talk therapy alone struggles to address.</p><p>Dr. Bessel van der Kolk, a leading trauma researcher, emphasizes that trauma is stored in the body and nervous system, not just the mind. Without addressing the somatic component, healing remains incomplete. For immigrants who have endured trauma related to their migration experience, somatic therapy offers a pathway to reclaim safety and regulation inside their own bodies.</p><h2>What Is Somatic Therapy?</h2><p>Somatic therapy is a body-centered approach to trauma healing rooted in neuroscience and attachment theory. It recognizes that trauma disrupts the autonomic nervous system's regulation, leading to symptoms like hypervigilance, numbness, chronic pain, or dissociation. Unlike psychotherapy focused solely on cognition and verbal processing, somatic therapy works with bodily sensations, movement, breath, and awareness to restore regulation and integration.</p><p>Peter Levine, the founder of Somatic Experiencing, describes trauma as a \"stuck\" state in the nervous system where the natural defensive responses of fight, flight, or freeze were overwhelmed or incomplete. Somatic therapy helps release that stuck energy and restore the nervous system’s natural ability to self-regulate.</p><h2>Why Survivors of Immigration Trauma Need Somatic Therapy</h2><p>Immigration trauma is often compounded by chronic uncertainty, systemic oppression, and social isolation. These factors keep the nervous system in a prolonged state of activation or shutdown. Survivors may experience:</p><ul><li>Persistent anxiety and hypervigilance</li><li>Somatic symptoms such as headaches, stomach pain, or muscle tension</li><li>Emotional numbing or dissociation</li><li>Difficulty feeling safe in their own bodies and environments</li><li>Triggers related to memories of detention, border crossing, or family separation</li></ul><p>Dr. Gabor Maté highlights that trauma responses are deeply embedded in the body’s biochemistry and nervous system. Somatic therapy addresses this by focusing on internal sensations and restoring a sense of safety and control, which is often shattered in immigration trauma.</p><h2>How Somatic Therapy Works for Immigration Trauma</h2><p>Somatic therapy uses a range of techniques to help survivors reconnect with their bodies and regulate their nervous system:</p><ul><li><strong>Tracking Sensations:</strong> Clients learn to identify and track physical sensations related to trauma without becoming overwhelmed.</li><li><strong>Resourcing:</strong> Building internal resources and external supports to create a felt sense of safety.</li><li><strong>Breathwork and Movement:</strong> Using breath and gentle movement to discharge trapped energy and shift nervous system states.</li><li><strong>Mindful Awareness:</strong> Cultivating present-moment awareness to reduce dissociation and increase embodiment.</li><li><strong>Window of Tolerance:</strong> Therapists help clients stay within the optimal arousal zone where healing can occur without retraumatization, a concept discussed extensively by Dr. Dan Siegel and Dr. Deb Dana.</li></ul><p>These interventions are tailored to the client's pace, honoring cultural contexts and the unique challenges faced by immigrant survivors.</p><h2>The Role of the Polyvagal Theory</h2><p>Stephen Porges’ Polyvagal Theory offers crucial insights into how the autonomic nervous system responds to trauma. It describes three neural pathways regulating our responses: the ventral vagal (social engagement), sympathetic (fight or flight), and dorsal vagal (shutdown or freeze).</p><p>Immigration trauma often triggers dysregulation across these systems, leaving survivors stuck in defensive states that manifest as anxiety, dissociation, or withdrawal. Somatic therapy, informed by the Polyvagal framework, helps clients access the ventral vagal system to reconnect with safety and social engagement.</p><blockquote>“Trauma is not what happens to you, but what happens inside you as a result of what happens to you.” – Dr. Gabor Maté</blockquote><h2>Practical Somatic Tools for Survivors</h2><p>Survivors can begin somatic healing even outside therapy sessions by learning simple practices that regulate the nervous system:</p><ul><li><strong>Grounding Exercises:</strong> Feeling the feet on the floor, noticing the contact points of the body, or holding a grounding object.</li><li><strong>Breath Awareness:</strong> Slow, deep, diaphragmatic breathing to activate the parasympathetic nervous system.</li><li><strong>Body Scans:</strong> Mindfully scanning the body to notice areas of tension or numbness without judgment.</li><li><strong>Safe Place Visualization:</strong> Imagining a location where one feels completely safe and relaxed, supporting nervous system regulation.</li></ul><p>These tools build resilience and help survivors regain a sense of control over their internal experience.</p><h2>Cultural Sensitivity in Somatic Therapy</h2><p>Immigration trauma is inseparable from cultural identity, language barriers, and systemic oppression. Therapists must approach somatic work with cultural humility and awareness. As Pat Ogden notes, somatic therapy must be adapted to honor the client’s cultural narratives and embodied expressions of trauma.</p><p>Language differences can affect how clients describe sensations or emotions, so therapists often rely more heavily on nonverbal cues and bodily experiences. Community support and culturally congruent healing practices can be integrated to strengthen outcomes.</p><h2>Integrating Somatic Therapy with Other Modalities</h2><p>Somatic therapy is most effective when combined with other trauma-informed approaches. For example:</p><ul><li><strong>Internal Family Systems (IFS):</strong> Richard Schwartz’s model works with internal parts and can be paired with somatic awareness to access and soothe trauma-held parts.</li><li><strong>EMDR:</strong> Francine Shapiro’s Eye Movement Desensitization and Reprocessing can be enhanced by somatic regulation before and after processing traumatic memories.</li><li><strong>Mindfulness and Meditation:</strong> Practices that cultivate present-moment awareness support somatic integration and nervous system regulation.</li></ul><p>The goal is a holistic healing that addresses mind, body, and relational contexts.</p><h2>Conclusion: Toward Embodied Healing and Resilience</h2><p>Immigration trauma leaves deep imprints on the body and nervous system that traditional talk therapy often cannot fully reach. Somatic therapy offers survivors a direct way to heal the physical and emotional wounds by restoring nervous system regulation and cultivating a felt sense of safety.</p><p>Grounded in the research of van der Kolk, Levine, Porges, Maté, and others, somatic therapy is a powerful approach for survivors who have felt stuck in their recovery. It empowers them to reclaim their bodies, feel more present, and build resilience for the challenges ahead.</p><p>Healing immigration trauma is not only possible—it is essential for survivors to thrive in their new lives.</p>", "faqs": [{"q": "How does somatic therapy differ from traditional talk therapy for trauma?", "a": "Somatic therapy focuses on bodily sensations and nervous system regulation, whereas traditional talk therapy centers on cognitive processing and verbal expression. It addresses trauma stored in the body, which talk therapy alone may miss."}, {"q": "Can somatic therapy help with symptoms like anxiety and dissociation related to immigration trauma?", "a": "Yes, somatic therapy helps regulate the nervous system, reducing anxiety and dissociation by teaching clients to stay within their window of tolerance and reconnect with their bodily sensations safely."}, {"q": "Is somatic therapy culturally sensitive to the unique experiences of immigrant survivors?", "a": "Effective somatic therapy incorporates cultural humility and adapts techniques to respect clients’ cultural backgrounds, language differences, and trauma narratives, ensuring a safe and relevant healing environment."}, {"q": "What are some simple somatic tools survivors can practice at home?", "a": "Grounding exercises, breath awareness, body scans, and safe place visualizations are accessible tools that survivors can use to regulate their nervous system and build resilience outside therapy."}], "affiliateProducts": [{"title": "Healing Trauma: A Pioneering Program for Restoring the Wisdom of Your Body", "asin": "B0016XUMJI", "description": "Peter Levine's foundational book introduces Somatic Experiencing and practical approaches for resolving trauma stored in the body."}, {"title": "The Body Keeps the Score: Brain, Mind, and Body in the Healing of Trauma", "asin": "B00G7V7H3W", "description": "Bessel van der Kolk's seminal work explains how trauma impacts the body and offers pathways to healing through body-centered therapies."}, {"title": "Polyvagal Exercises for Safety and Connection: 50 Client-Centered Practices", "asin": "B07V3Z9V8M", "description": "Deb Dana provides practical exercises grounded in Polyvagal Theory to support nervous system regulation and trauma recovery."}], "metaTitle": "Somatic Therapy for Immigration Trauma Survivors", "metaDescription": "Discover how somatic therapy helps survivors of immigration trauma heal by regulating the nervous system and addressing trauma stored in the body.", "hero_url": "https://somatic-forlife.b-cdn.net/images/hero-trauma-therapy.webp", "author": "The Oracle Lover"}