{"slug": "somatic-therapy-for-survivors-of-childhood-emotional-neglect-by-developmental-culture", "title": "Somatic Therapy for Survivors of Childhood Emotional Neglect by Developmental Culture", "category": "Trauma Therapy", "excerpt": "Explore how somatic therapy addresses childhood emotional neglect by healing the body’s trauma imprint and restoring nervous system regulation.", "readTime": "9 min read", "body": "<h2>Understanding Childhood Emotional Neglect (CEN)</h2><p>Childhood Emotional Neglect (CEN) is a form of trauma that often flies under the radar. Unlike physical or sexual abuse, it’s characterized by the absence of emotional support, validation, and attunement from caregivers during critical developmental years. This neglect leaves a deep imprint on the nervous system, shaping how survivors relate to themselves and others.</p><p>Dr. Jonice Webb, a leading researcher on CEN, defines it as “what happens when parents fail to respond enough to a child’s emotional needs.” It’s not about what happened to you but what didn’t happen — the emotional nourishment that was missing. This lack creates an internal void that can manifest as chronic feelings of emptiness, shame, and difficulty identifying or expressing emotions.</p><h2>The Developmental Culture of Emotional Neglect</h2><p>Developmental culture refers to the broader environment—including family dynamics, societal norms, and cultural expectations—that influences a child’s growth. In many developmental cultures, especially those valuing stoicism or emotional restraint, children’s emotional needs may be routinely minimized or dismissed. This cultural context compounds the effects of CEN, making it harder for survivors to even recognize their unmet needs.</p><p>Research from Bessel van der Kolk emphasizes that trauma is stored not just in the mind but in the body’s physiology. When emotional needs are neglected, the body remains in a state of dysregulation, often hypervigilant or numb, because it never learned to integrate emotional experiences safely.</p><h3>How CEN Shapes the Nervous System</h3><p>Stephen Porges’ Polyvagal Theory explains how the nervous system responds to threat and safety. For survivors of CEN, the nervous system often defaults to defensive states—either immobilization (shutdown) or hyperarousal (anxiety, agitation). This is because the body never fully experienced co-regulation with a caregiver, which is essential for developing a resilient autonomic nervous system.</p><p>Deb Dana, a clinician who applies Polyvagal Theory in trauma therapy, notes that without early attuned responses, the nervous system lacks a reliable sense of safety. This leads to chronic dysregulation, which can present as emotional numbness, difficulty trusting others, or an inability to self-soothe.</p><h2>Why Traditional Talk Therapy Often Feels Insufficient</h2><p>Many survivors of CEN report feeling stuck in traditional therapy. They can intellectually understand their history but remain disconnected from their feelings and bodily sensations. This disconnect is because emotional neglect affects somatic memory — how trauma is encoded in the body, not just the mind.</p><p>Pat Ogden, founder of Sensorimotor Psychotherapy, highlights that trauma is fundamentally a body-based experience. Without addressing the body’s implicit memories and physiological patterns, talk therapy may only scratch the surface.</p><h2>Somatic Therapy: Healing Where Words Fall Short</h2><p>Somatic therapy focuses on the body’s sensations, movements, and nervous system responses to release trauma. It provides tools to restore nervous system regulation, reconnect survivors to their felt experience, and develop new patterns of safety and self-compassion.</p><p>Peter Levine, a pioneer in somatic experiencing, explains that trauma is stuck energy in the nervous system. Somatic therapy helps discharge this energy safely, enabling the survivor to reclaim bodily autonomy and emotional presence.</p><blockquote>“Healing trauma requires reconnecting with the body’s wisdom, not just the mind’s understanding.” — Peter Levine</blockquote><h3>Core Somatic Approaches for CEN Survivors</h3><ul><li><strong>Tracking Sensations:</strong> Learning to notice and name physical sensations creates a bridge between body and mind.</li><li><strong>Resourcing:</strong> Identifying internal or external sources of safety to anchor the nervous system in moments of distress.</li><li><strong>Movement and Breath Work:</strong> Using gentle movement and breath to regulate autonomic arousal and release tension.</li><li><strong>Interoceptive Awareness:</strong> Building awareness of internal bodily states to strengthen emotional literacy.</li><li><strong>Co-regulation Practices:</strong> Engaging with attuned presence, either through therapist or safe relationships, to retrain the nervous system.</li></ul><h2>Developmental Culture and Somatic Therapy: A Synergistic Approach</h2><p>Integrating an understanding of developmental culture into somatic therapy deepens healing. It helps survivors contextualize their emotional neglect as not a personal failing but a systemic pattern passed through generations or cultural norms.</p><p>Gabor Maté emphasizes that trauma is relational and cultural. Healing requires reclaiming connection—both to self and community. Somatic therapy offers the embodied tools, while awareness of developmental culture provides compassionate context and meaning.</p><h3>Addressing Shame and Self-Blame</h3><p>Shame is a core wound in CEN survivors. Francine Shapiro, developer of EMDR therapy, notes that trauma-related shame is often stored somatically and can keep survivors stuck in self-critical loops.</p><p>Somatic therapy helps by gently uncovering these shame-based sensations and holding them with curiosity and compassion rather than judgment. This process gradually undermines shame’s power and fosters a sense of intrinsic worth.</p><h2>Practical Steps for Self-Directed Somatic Healing</h2><p>If you’ve tried talk therapy and still feel stuck, incorporating somatic practices can be a game-changer. Here are some accessible ways to start:</p><ul><li><strong>Body Scan Meditation:</strong> Spend 5-10 minutes daily noticing sensations from head to toe without trying to change them.</li><li><strong>Grounding Exercises:</strong> Use breath, touch (like holding your hands or a soft object), or feeling your feet on the floor to anchor yourself in the present.</li><li><strong>Journaling Sensations:</strong> Write about bodily experiences during emotional moments to increase interoceptive awareness.</li><li><strong>Mindful Movement:</strong> Gentle yoga, walking, or stretching can help release tension and increase body connection.</li><li><strong>Seek Attuned Support:</strong> If possible, work with a therapist trained in somatic approaches or find community spaces that offer co-regulation.</li></ul><h2>Conclusion: Reclaiming Emotional Wholeness Through the Body</h2><p>Childhood emotional neglect leaves invisible scars that traditional talk therapy often misses. Somatic therapy offers a path to reclaiming emotional wholeness by addressing the body’s trauma imprint and restoring nervous system regulation.</p><p>By understanding the developmental culture that shaped your experience and applying somatic tools, you can move beyond feeling stuck and rediscover a sense of safety, connection, and emotional vitality.</p><p>As Dan Siegel reminds us, <em>“Integration is the key to healing.”</em> Somatic therapy is a powerful way to integrate mind, body, and culture in your healing journey.</p>", "faqs": [{"q": "What is childhood emotional neglect and how does it affect adults?", "a": "Childhood emotional neglect occurs when caregivers fail to meet a child's emotional needs, leading to difficulties in emotional regulation, self-awareness, and relationships in adulthood."}, {"q": "How does somatic therapy differ from traditional talk therapy for CEN?", "a": "Somatic therapy focuses on bodily sensations and nervous system regulation, addressing trauma stored in the body rather than just cognitive understanding."}, {"q": "Can somatic therapy be done on my own, or do I need a therapist?", "a": "While somatic therapy is most effective with trained guidance, many self-directed practices like body scans and grounding exercises can support healing independently."}, {"q": "What role does developmental culture play in emotional neglect?", "a": "Developmental culture shapes norms and expectations around emotional expression, which can normalize neglectful behaviors and impact how emotional needs are met or missed."}], "affiliateProducts": [{"title": "The Body Keeps the Score by Bessel van der Kolk", "asin": "0143127748", "description": "A foundational book that explains how trauma is stored in the body and offers insights into somatic healing."}, {"title": "Waking the Tiger by Peter Levine", "asin": "155643233X", "description": "A guide to understanding and healing trauma through somatic experiencing techniques."}, {"title": "Polyvagal Exercises for Safety and Connection by Deb Dana", "asin": "1941525579", "description": "Practical tools based on Polyvagal Theory to help regulate the nervous system and build safety."}], "metaTitle": "Somatic Therapy for Childhood Emotional Neglect", "metaDescription": "Discover how somatic therapy heals childhood emotional neglect by restoring nervous system regulation and body awareness.", "hero_url": "https://somatic-forlife.b-cdn.net/images/hero-trauma-therapy.webp", "author": "The Oracle Lover"}